tschm/__init__.py
tschm/config/__init__.py
tschm/config/config.py
tschm/config/templates/休眠脚本.ps1
tschm/config/templates/倒计时休眠脚本.ps1
tschm/config/templates/倒计时关机脚本.ps1
tschm/config/templates/关机脚本.ps1
tschm/config/templates/定时同步uvtools.ps1
tschm/config/templates/定时同步全局安装的npm包.ps1
tschm/decorators/singleton.py
tschm-4.0.3.dist-info/WHEEL
tschm-4.0.3.dist-info/entry_points.txt
tschm-4.0.3.dist-info/METADATA
tschm-4.0.3.dist-info/RECORD
