Metadata-Version: 2.3
Name: tschm
Version: 4.0.3
Summary: windows定时任务管理器 即使电脑睡眠也能运行的定时任务管理器
Author: lipanpan
Author-email: lipanpan <lipanpanmail@163.com>
Requires-Dist: fire>=0.7.1
Requires-Dist: pywin32>=311
Requires-Dist: toml>=0.10.2
Requires-Python: >=3.13
